strangeworks_vqe/__init__.py
strangeworks_vqe/sdk.py
strangeworks_vqe/serializer.py
strangeworks_vqe/utils.py
strangeworks_vqe-0.1.7.dist-info/METADATA
strangeworks_vqe-0.1.7.dist-info/WHEEL
strangeworks_vqe-0.1.7.dist-info/RECORD
