Metadata-Version: 2.4
Name: strangeworks-vqe
Version: 0.1.7
Summary: Extension to strangeworks sdk to allow user to run qaoa service
Author: SFlann
Author-email: stuart@strangeworks.com
Requires-Python: >=3.10,<4.0
Classifier: Programming Language :: Python :: 3
Classifier: Programming Language :: Python :: 3.10
Classifier: Programming Language :: Python :: 3.11
Classifier: Programming Language :: Python :: 3.12
Classifier: Programming Language :: Python :: 3.13
Classifier: Programming Language :: Python :: 3.14
Requires-Dist: networkx (>=3.0,<4.0)
Requires-Dist: qiskit (==0.41.0)
Requires-Dist: strangeworks (>=0.6.1,<0.7.0)
